{
  "weapons": {
    "unarmedAttacks": [
      {
        "name": "Fist",
        "level": 0,
        "price": 0,
        "damage": "1d4 B",
        "hands": "1",
        "bulk": "-",
        "group": "Brawling",
        "traits": ["Agile", "Finesse", "Nonlethal", "Unarmed"],
        "description": "An unarmed attack uses your body rather than a manufactured weapon.",
        "source": "Player Core",
        "category": "Unarmed Attack"
      }
    ],
    "simpleMelee": [
      {
        "name": "Baton",
        "level": 0,
        "price": 2,
        "damage": "1d6 B",
        "bulk": "L",
        "hands": "1",
        "upgrades": 1,
        "group": "Club",
        "traits": ["Analog", "Finesse", "Nonlethal", "Parry"],
        "description": "This reinforced rod is commonly made from metal alloys and designed to strike and parry incoming blows.",
        "source": "Player Core",
        "category": "Simple Melee Weapon"
      },
      {
        "name": "Battleglove",
        "level": 0,
        "price": 3,
        "damage": "1d4 B",
        "bulk": "-",
        "hands": "1",
        "upgrades": 1,
        "group": "Brawling",
        "traits": ["Agile", "Analog", "Free-Hand"],
        "description": "These durable gloves fit over a wielder’s hands (or other appendages) and feature weighted plates or spikes over the knuckles.",
        "source": "Player Core",
        "category": "Simple Melee Weapon"
      },
      {
        "name": "Knife",
        "level": 0,
        "price": 2,
        "damage": "1d4 P",
        "bulk": "L",
        "hands": "1",
        "upgrades": 1,
        "group": "Knife",
        "traits": ["Agile", "Analog", "Finesse", "Thrown 10 ft.", "Versatile S"],
        "description": "Invaluable as both a weapon and a tool, knives come in a variety of shapes, styles, and materials ranging from starmetals to ceramics.",
        "source": "Player Core",
        "category": "Simple Melee Weapon"
      },
      {
        "name": "Puzzleblade",
        "level": 0,
        "price": 15,
        "damage": "1d8 S",
        "bulk": "1",
        "hands": "2",
        "upgrades": 1,
        "group": "Sword",
        "traits": ["Analog", "Breakdown", "Kasatha"],
        "description": "This kasathan sword breaks down into interlocking pieces for storage and transport.",
        "source": "Player Core",
        "category": "Simple Melee Weapon"
      },
      {
        "name": "Shock pad",
        "level": 0,
        "price": 10,
        "damage": "1d4 E",
        "bulk": "-",
        "hands": "1",
        "upgrades": 1,
        "group": "Shock",
        "traits": ["Agile", "Free-Hand", "Powered", "Tech"],
        "description": "This flexible nanocarbon circuit can be installed as an upgrade into gloves, kneepads, or similar appendage protectors to emit a powerful electric shock.",
        "source": "Player Core",
        "category": "Simple Melee Weapon"
      },
      {
        "name": "Zero knife",
        "level": 0,
        "price": 12,
        "damage": "1d4 C",
        "bulk": "L",
        "hands": "1",
        "upgrades": 1,
        "group": "Cryo",
        "traits": ["Agile", "Finesse", "Powered", "Tech", "Versatile P"],
        "description": "Unfolding like a switchblade, a supercooled chamber within this weapon instantly forms a blade of ice.",
        "source": "Player Core",
        "category": "Simple Melee Weapon"
      }
    ],
    "martialMelee": [
      {
        "name": "Aucturnite chakram",
        "level": 0,
        "price": 15,
        "damage": "1d6 S",
        "bulk": "L",
        "hands": "1",
        "upgrades": 1,
        "group": "Knife",
        "traits": ["Analog", "Critical (mental)", "Thrown 20 ft."],
        "description": "This bladed hoop is carved from a chunk of aucturnite and sculpted to resemble a planet’s ring.",
        "source": "Player Core",
        "category": "Martial Melee Weapon"
      },
      {
        "name": "Battle ribbon",
        "level": 0,
        "price": 5,
        "damage": "1d4 S",
        "bulk": "L",
        "hands": "1",
        "upgrades": 1,
        "group": "Flail",
        "traits": ["Analog", "Finesse", "Nonlethal", "Reach", "Trip"],
        "description": "This sheer nanocarbon ribbon is sharp enough to cut through flesh without interrupting the traditional battle dances that make the weapon famous.",
        "source": "Player Core",
        "category": "Martial Melee Weapon"
      },
      {
        "name": "Bone scepter",
        "level": 0,
        "price": 5,
        "damage": "1d6 Modular",
        "bulk": "L",
        "hands": "1",
        "upgrades": 1,
        "group": "Club",
        "traits": ["Analog", "Modular (B, P, or S)"],
        "description": "This engraved club of solid bone is tempered using material from the void that can drain life energy.",
        "source": "Player Core",
        "category": "Martial Melee Weapon"
      },
      {
        "name": "Doshko",
        "level": 0,
        "price": 20,
        "damage": "1d12 P",
        "bulk": "1",
        "hands": "2",
        "upgrades": 1,
        "group": "Axe",
        "traits": ["Analog", "Parry", "Vesk"],
        "description": "The traditional weapon of the Veskarium, this powered poleaxe features one to three triangular blades forged for both wide overhead swings and tactical parrying.",
        "source": "Player Core",
        "category": "Martial Melee Weapon"
      },
      {
        "name": "Dueling sword",
        "level": 0,
        "price": 10,
        "damage": "1d8 S",
        "bulk": "1",
        "hands": "1",
        "upgrades": 1,
        "group": "Sword",
        "traits": ["Analog", "Versatile P"],
        "description": "Coming in a variety of styles, these traditional and time-tested weapons have been honed with advanced smithing techniques and modern materials.",
        "source": "Player Core",
        "category": "Martial Melee Weapon"
      },
      {
        "name": "Fangblade",
        "level": 0,
        "price": 27,
        "damage": "1d10 S",
        "bulk": "1",
        "hands": "2",
        "upgrades": 1,
        "group": "Axe",
        "traits": ["Backswing", "Boost 1d12", "Powered", "Tech"],
        "description": "Durable teeth line the edges of this motorized sword and spin with the force of an industrial chainsaw.",
        "source": "Player Core",
        "category": "Martial Melee Weapon"
      },
      {
        "name": "Force needle",
        "level": 0,
        "price": 15,
        "damage": "1d4 P",
        "bulk": "1",
        "hands": "1",
        "upgrades": 1,
        "group": "Dart",
        "traits": ["Agile", "Backstabber", "Concealable", "Finesse", "Injection", "Tech", "Ysoki"],
        "description": "When a full vial of liquid is inserted into the bottom of this weapon’s hilt, it creates an energy needle to hold and inject its payload.",
        "source": "Player Core",
        "category": "Martial Melee Weapon"
      },
      {
        "name": "Nano-edge rapier",
        "level": 0,
        "price": 25,
        "damage": "1d6 P",
        "bulk": "1",
        "hands": "1",
        "upgrades": 1,
        "group": "Sword",
        "traits": ["Analog", "Deadly d8", "Disarm", "Finesse"],
        "description": "The edge of this precision-crafted foil is sharpened to the thickness of a single atom, using regenerating nanites to maintain itself.",
        "source": "Player Core",
        "category": "Martial Melee Weapon"
      },
      {
        "name": "Painglaive",
        "level": 0,
        "price": 30,
        "damage": "1d10 S",
        "bulk": "1",
        "hands": "2",
        "upgrades": 1,
        "group": "Polearm",
        "traits": ["Boost 1d10", "Powered", "Reach", "Tech"],
        "description": "This fierce but deceptively elegant polearm rips apart enemies with a motor-powered fangblade. An adjustable pulse trigger allows the wielder to channel extra pain.",
        "source": "Player Core",
        "category": "Martial Melee Weapon"
      },
      {
        "name": "Phase cutlass",
        "level": 0,
        "price": 18,
        "damage": "1d6 Modular",
        "bulk": "1",
        "hands": "1",
        "upgrades": 1,
        "group": "Sword",
        "traits": ["Analog", "Deadly d6", "Modular (S and analog, or V, powered, and tech)", "Sweep"],
        "description": "A phase cutlass resembles a traditional curved sword until it’s powered. Then its blade morphs into a shimmering void.",
        "source": "Player Core",
        "category": "Martial Melee Weapon"
      },
      {
        "name": "Plasma doshko",
        "level": 0,
        "price": 30,
        "damage": "1d10 F",
        "bulk": "1",
        "hands": "2",
        "upgrades": 1,
        "group": "Axe",
        "traits": ["Critical (plasma)", "Powered", "Sweep", "Tech", "Vesk"],
        "description": "Unlike a traditional doshko, this poleaxe uses blades of magnetically stabilized plasma that spin to cleave through multiple enemies with ease.",
        "source": "Player Core",
        "category": "Martial Melee Weapon"
      },
      {
        "name": "Plasma sword",
        "level": 0,
        "price": 15,
        "damage": "1d8 F",
        "bulk": "L",
        "hands": "1",
        "upgrades": 1,
        "group": "Sword",
        "traits": ["Critical (plasma)", "Powered", "Tech"],
        "description": "This sword generates a focused beam of plasma around a localized force field powered by a generator in the sword’s hilt.",
        "source": "Player Core",
        "category": "Martial Melee Weapon"
      },
      {
        "name": "Polyglove",
        "level": 0,
        "price": 20,
        "damage": "1d6 E",
        "bulk": "L",
        "hands": "1",
        "upgrades": 1,
        "group": "Shock",
        "traits": ["Arc", "Powered", "Professional (Computers)", "Tech"],
        "description": "This glove features dozens of delicate tools for building or repairing computers. Overclocking it generates voltage between fingertips.",
        "source": "Player Core",
        "category": "Martial Melee Weapon"
      },
      {
        "name": "Pulse gauntlet",
        "level": 0,
        "price": 15,
        "damage": "1d4 So",
        "bulk": "-",
        "hands": "1",
        "upgrades": 1,
        "group": "Sonic",
        "traits": ["Agile", "Critical (brawling)", "Free-Hand", "Powered", "Shove", "Tech", "Trip"],
        "description": "Popularized in underground fighting circles, this heavy-duty nanocarbon glove amplifies and weaponizes sounds made by its wielder.",
        "source": "Player Core",
        "category": "Martial Melee Weapon"
      },
      {
        "name": "Shock truncheon",
        "level": 0,
        "price": 16,
        "damage": "1d6 E",
        "bulk": "L",
        "hands": "1",
        "upgrades": 1,
        "group": "Club",
        "traits": ["Disarm", "Modular (arc or nonlethal)", "Powered", "Tech"],
        "description": "Popular among security forces, this retractable baton discharges electricity with each Strike.",
        "source": "Player Core",
        "category": "Martial Melee Weapon"
      },
      {
        "name": "Singing spear",
        "level": 0,
        "price": 20,
        "damage": "1d6 Modular",
        "bulk": "1",
        "hands": "2",
        "upgrades": 1,
        "group": "Spear",
        "traits": ["Modular (P, analog and thrown 20 ft., or So, boost 1d10, critical (sonic), powered and tech)"],
        "description": "Classically shaped like an oversized musical note, this spear intones melodious pitches when it strikes.",
        "source": "Player Core",
        "category": "Martial Melee Weapon"
      },
      {
        "name": "Tailblade",
        "level": 0,
        "price": 10,
        "damage": "1d4 S",
        "bulk": "-",
        "hands": "0",
        "upgrades": 1,
        "group": "Knife",
        "traits": ["Agile", "Analog", "Finesse", "Free-Hand"],
        "description": "Adjustable bands secure this lightweight blade to a tail, tentacle, or similar appendage.",
        "source": "Player Core",
        "category": "Martial Melee Weapon"
      },
      {
        "name": "Talon",
        "level": 0,
        "price": 20,
        "damage": "1d6 Modular",
        "bulk": "L",
        "hands": "1",
        "upgrades": 1,
        "group": "Knife",
        "traits": ["Agile", "Finesse", "Modular (A, critical (corrosive), tech, or S and analog)"],
        "description": "This stylized knife tapers into a curved and serrated blade. When powered, it spews a highly corrosive acid.",
        "source": "Player Core",
        "category": "Martial Melee Weapon"
      }
    ],
    "advancedMelee": [
      {
        "name": "Disintegration lash",
        "level": 0,
        "price": 32,
        "damage": "1d6 A",
        "bulk": "L",
        "hands": "1",
        "upgrades": 1,
        "group": "Corrosive",
        "traits": ["Disarm", "Finesse", "Powered", "Razing", "Reach", "Tech"],
        "description": "Appearing as an undulating black snake when powered, this whip crackles with red-tinged energy that sunders whatever it strikes.",
        "source": "Player Core",
        "category": "Advanced Melee Weapon"
      },
      {
        "name": "Grindblade",
        "level": 0,
        "price": 25,
        "damage": "1d8 S",
        "bulk": "1",
        "hands": "1",
        "upgrades": 1,
        "group": "Sword",
        "traits": ["Analog", "Critical (knife)", "Fatal d12"],
        "description": "The edge of this broad-tipped sword is composed of micro-splitting nanoparticles that slice apart targets with surgical precision.",
        "source": "Player Core",
        "category": "Advanced Melee Weapon"
      },
      {
        "name": "Skyfire sword",
        "level": 0,
        "price": 30,
        "damage": "1d8 F",
        "bulk": "1",
        "hands": "1",
        "upgrades": 1,
        "group": "Flame",
        "traits": ["Deadly d8", "Two-Hand d10", "Powered", "Tech"],
        "description": "Famously wielded by warriors of the Skyfire Legion, this flaming blade is powered by burning gas held in place by magnetic fields.",
        "source": "Player Core",
        "category": "Advanced Melee Weapon"
      },
      {
        "name": "Thermal dynafan",
        "level": 0,
        "price": 15,
        "damage": "1d6 Modular",
        "bulk": "L",
        "hands": "1",
        "upgrades": 1,
        "group": "Cryo",
        "traits": ["Agile", "Concealable", "Finesse", "Powered", "Tech", "Twin", "Modular (F and critical (flame), or C)"],
        "description": "This warfan is a modified handheld environmental comfort device that changes the pressure in the air to create a frigid chill or a brilliant plume of fire.",
        "source": "Player Core",
        "category": "Advanced Melee Weapon"
      }
    ],
    "simpleRanged": [
      {
        "name": "Acid dart rifle",
        "level": 0,
        "price": 40,
        "damage": "1d8 A",
        "range": "80 ft.",
        "reload": 1,
        "bulk": "1",
        "hands": "2",
        "magazine": "5 projectiles",
        "expend": 1,
        "upgrades": 1,
        "group": "Corrosive",
        "traits": ["Analog"],
        "description": "Uses compressed air to shoot tiny, chambered darts loaded with components for a highly corrosive compound.",
        "source": "Player Core",
        "category": "Simple Ranged Weapon"
      },
      {
        "name": "Arc pistol",
        "level": 0,
        "price": 25,
        "damage": "1d4 E",
        "range": "30 ft.",
        "reload": 1,
        "bulk": "1",
        "hands": "1",
        "magazine": "10 charges",
        "expend": 2,
        "upgrades": 1,
        "group": "Shock",
        "traits": ["Arc", "Tech"],
        "description": "Instead of traditional ammunition, this bulky pistol contains a capacitor that generates arcs of electricity.",
        "source": "Player Core",
        "category": "Simple Ranged Weapon"
      },
      {
        "name": "Arc rifle",
        "level": 0,
        "price": 50,
        "damage": "1d6 E",
        "range": "50 ft.",
        "reload": 1,
        "bulk": "2",
        "hands": "2",
        "magazine": "10 charges",
        "expend": 2,
        "upgrades": 1,
        "group": "Shock",
        "traits": ["Arc", "Tech"],
        "description": "This rifle’s oversized body contains a larger version of an arc pistol capacitor, with a short barrel and polycarbon stock.",
        "source": "Player Core",
        "category": "Simple Ranged Weapon"
      },
      {
        "name": "Autotarget rifle",
        "level": 0,
        "price": 45,
        "damage": "1d6 P",
        "range": "30 ft.",
        "reload": 2,
        "bulk": "2",
        "hands": "2",
        "magazine": "20 projectiles",
        "expend": 1,
        "upgrades": 1,
        "group": "Projectile",
        "traits": ["Analog", "Automatic"],
        "description": "This short, bulky assault rifle incorporates a piston system that allows the user to switch to auto-fire.",
        "source": "Player Core",
        "category": "Simple Ranged Weapon"
      },
      {
        "name": "Crossbolter",
        "level": 0,
        "price": 25,
        "damage": "1d10 P",
        "range": "100 ft.",
        "reload": 1,
        "bulk": "2",
        "hands": "2",
        "magazine": "1 projectile",
        "expend": 1,
        "upgrades": 1,
        "group": "Crossbow",
        "traits": ["Analog"],
        "description": "This high-tech crossbow uses a series of pistons to propel bolts along its barrel.",
        "source": "Player Core",
        "category": "Simple Ranged Weapon"
      },
      {
        "name": "Laser pistol",
        "level": 0,
        "price": 30,
        "damage": "1d6 F",
        "range": "40 ft.",
        "reload": 1,
        "bulk": "1",
        "hands": "1",
        "magazine": "10 charges",
        "expend": 2,
        "upgrades": 1,
        "group": "Laser",
        "traits": ["Tech"],
        "description": "This compact pistol is the most popular sidearm in the Pact Worlds thanks to its reliability, durability, and affordability.",
        "source": "Player Core",
        "category": "Simple Ranged Weapon"
      },
      {
        "name": "Laser rifle",
        "level": 0,
        "price": 45,
        "damage": "1d8 F",
        "range": "100 ft.",
        "reload": 1,
        "bulk": "2",
        "hands": "2",
        "magazine": "10 charges",
        "expend": 2,
        "upgrades": 1,
        "group": "Laser",
        "traits": ["Tech"],
        "description": "These dependable, mass-produced rifles shoot concentrated beams of energy out of square-shaped barrels.",
        "source": "Player Core",
        "category": "Simple Ranged Weapon"
      },
      {
        "name": "Pulsecaster pistol",
        "level": 0,
        "price": 30,
        "damage": "1d6 E",
        "range": "30 ft.",
        "reload": 1,
        "bulk": "1",
        "hands": "1",
        "magazine": "10 charges",
        "expend": 2,
        "upgrades": 1,
        "group": "Shock",
        "traits": ["Nonlethal", "Tech"],
        "description": "This imposing pistol fires a jolt of paralyzing electricity from its barrel.",
        "source": "Player Core",
        "category": "Simple Ranged Weapon"
      },
      {
        "name": "Reaction breacher",
        "level": 0,
        "price": 45,
        "damage": "1d8 B",
        "range": "100 ft.",
        "reload": 1,
        "bulk": "2",
        "hands": "2",
        "magazine": "3 projectiles",
        "expend": 1,
        "upgrades": 1,
        "group": "Projectile",
        "traits": ["Concussive", "Razing", "Tech"],
        "description": "This portable reaction cannon launches flak from miniature cluster missiles that rip through a fortified structure.",
        "source": "Player Core",
        "category": "Simple Ranged Weapon"
      },
      {
        "name": "Scattergun",
        "level": 0,
        "price": 40,
        "damage": "1d8 P",
        "range": "15 ft.",
        "reload": 1,
        "bulk": "1",
        "hands": "2",
        "magazine": "4 projectiles",
        "expend": 1,
        "upgrades": 1,
        "group": "Projectile",
        "traits": ["Analog", "Area (cone)", "Concussive", "Unwieldy"],
        "description": "A scattergun is a long-barreled firearm that fires numerous spherical projectiles to hit multiple targets.",
        "source": "Player Core",
        "category": "Simple Ranged Weapon"
      },
      {
        "name": "Seeker rifle",
        "level": 0,
        "price": 60,
        "damage": "1d10 P",
        "range": "120 ft.",
        "reload": 1,
        "bulk": "2",
        "hands": "2",
        "magazine": "1 projectile",
        "expend": 1,
        "upgrades": 1,
        "group": "Sniper",
        "traits": ["Analog", "Kickback", "Volley 30 ft."],
        "description": "This single-shot sniper rifle is one of the most popular weapons in the Vast thanks to its stability.",
        "source": "Player Core",
        "category": "Simple Ranged Weapon"
      },
      {
        "name": "Semi-auto pistol",
        "level": 0,
        "price": 30,
        "damage": "1d6 P",
        "range": "60 ft.",
        "reload": 1,
        "bulk": "L",
        "hands": "1",
        "magazine": "10 projectiles",
        "expend": 1,
        "upgrades": 1,
        "group": "Projectile",
        "traits": ["Analog"],
        "description": "This pistol automatically ejects used cartridges and loads new ammunition after every shot fired.",
        "source": "Player Core",
        "category": "Simple Ranged Weapon"
      },
      {
        "name": "Sonic rifle",
        "level": 0,
        "price": 40,
        "damage": "1d6 So",
        "range": "40 ft.",
        "reload": 1,
        "bulk": "1",
        "hands": "2",
        "magazine": "10 charges",
        "expend": 2,
        "upgrades": 1,
        "group": "Sonic",
        "traits": ["Boost 1d8", "Tech"],
        "description": "A sonic rifle creates a narrow beam of ultrasound that effectively turns whatever it hits into a speaker.",
        "source": "Player Core",
        "category": "Simple Ranged Weapon"
      },
      {
        "name": "Zero pistol",
        "level": 0,
        "price": 30,
        "damage": "1d6 C",
        "range": "30 ft.",
        "reload": 1,
        "bulk": "L",
        "hands": "1",
        "magazine": "10 chem",
        "expend": 2,
        "upgrades": 1,
        "group": "Cryo",
        "traits": ["Tech"],
        "description": "Zero pistols use transparent canisters of supercooled liquid as ammunition.",
        "source": "Player Core",
        "category": "Simple Ranged Weapon"
      }
    ],
    "martialRanged": [
      {
        "name": "Arc emitter",
        "level": 0,
        "price": 95,
        "damage": "1d8 E",
        "range": "20 ft.",
        "reload": 1,
        "bulk": "1",
        "hands": "2",
        "magazine": "10 charges",
        "expend": 2,
        "upgrades": 1,
        "group": "Shock",
        "traits": ["Area (cone)", "Nonlethal", "Unwieldy", "Tech"],
        "description": "Composed of two 4-foot-long protracting rails, this weapon shoots arcs of electricity at targets.",
        "source": "Player Core",
        "category": "Martial Ranged Weapon"
      },
      {
        "name": "Assassin rifle",
        "level": 0,
        "price": 100,
        "damage": "1d10 P",
        "range": "120 ft.",
        "reload": 1,
        "bulk": "1",
        "hands": "2",
        "magazine": "1 projectile",
        "expend": 1,
        "upgrades": 1,
        "group": "Sniper",
        "traits": ["Analog", "Backstabber", "Fatal d12", "Kickback", "Unwieldy", "Volley 30 ft."],
        "description": "This sniper rifle breaks down into small parts, allowing its wielder to smuggle the weapon without attracting attention.",
        "source": "Player Core",
        "category": "Martial Ranged Weapon"
      },
      {
        "name": "Boom pistol",
        "level": 0,
        "price": 30,
        "damage": "1d6 So",
        "range": "40 ft.",
        "reload": 1,
        "bulk": "1",
        "hands": "1",
        "magazine": "10 charges",
        "expend": 2,
        "upgrades": 1,
        "group": "Sonic",
        "traits": ["Boost 1d8", "Razing", "Tech"],
        "description": "Resembles a megaphone with a trigger, emitting sudden bursts of sound capable of shattering bulletproof glass.",
        "source": "Player Core",
        "category": "Martial Ranged Weapon"
      },
      {
        "name": "Breaching gun",
        "level": 0,
        "price": 30,
        "damage": "1d10 P",
        "range": "15 ft.",
        "reload": 1,
        "bulk": "1",
        "hands": "2",
        "magazine": "3 projectile",
        "expend": 1,
        "upgrades": 1,
        "group": "Projectile",
        "traits": ["Analog", "Concussive", "Kickback", "Ranged shove", "Razing"],
        "description": "This snub-nosed scattergun is commonly used to blast through doors and walls.",
        "source": "Player Core",
        "category": "Martial Ranged Weapon"
      },
      {
        "name": "Coil Rifle",
        "level": 0,
        "price": 100,
        "damage": "1d10 P",
        "range": "120 ft.",
        "reload": 1,
        "bulk": "1",
        "hands": "2",
        "magazine": "1 projectile",
        "expend": 1,
        "upgrades": 1,
        "group": "Sniper",
        "traits": ["Boost d10", "Kickback", "Tech", "Unwieldy", "Volley 30 ft."],
        "description": "The barrel of this rifle is surrounded by a coil that accelerates ammunition with power and accuracy using carefully aligned magnetic fields.",
        "source": "Player Core",
        "category": "Martial Ranged Weapon"
      },
      {
        "name": "Flamethrower",
        "level": 0,
        "price": 75,
        "damage": "1d10 F",
        "range": "15 ft.",
        "reload": 1,
        "bulk": "2",
        "hands": "2",
        "magazine": "10 chem",
        "expend": 2,
        "upgrades": 1,
        "group": "Flame",
        "traits": ["Area (cone)", "Tech", "Unwieldy"],
        "description": "This bulky, rifle-shaped weapon spews flames using a tank of highly combustible, pressurized chemicals housed in its stock.",
        "source": "Player Core",
        "category": "Martial Ranged Weapon"
      },
      {
        "name": "Machine gun",
        "level": 0,
        "price": 80,
        "damage": "1d8 P",
        "range": "40 ft.",
        "reload": 2,
        "bulk": "2",
        "hands": "2",
        "magazine": "20 projectiles",
        "expend": 1,
        "upgrades": 1,
        "group": "Projectile",
        "traits": ["Analog", "Automatic"],
        "description": "These proven and reliable automatic weapons are capable of firing in short bursts or completely emptying their magazines.",
        "source": "Player Core",
        "category": "Martial Ranged Weapon"
      },
      {
        "name": "Plasma caster",
        "level": 0,
        "price": 40,
        "damage": "1d8 F",
        "range": "60 ft.",
        "reload": 1,
        "bulk": "2",
        "hands": "2",
        "magazine": "10 charges",
        "expend": 2,
        "upgrades": 1,
        "group": "Plasma",
        "traits": ["Boost 1d10", "Tech"],
        "description": "This compact pistol shoots balls of condensed plasma.",
        "source": "Player Core",
        "category": "Martial Ranged Weapon"
      },
      {
        "name": "Rotating pistol",
        "level": 0,
        "price": 30,
        "damage": "1d6 P",
        "range": "60 ft.",
        "reload": 1,
        "bulk": "L",
        "hands": "1",
        "magazine": "6 projectiles",
        "expend": 1,
        "upgrades": 1,
        "group": "Projectile",
        "traits": ["Agile", "Analog", "Concealable", "Concussive"],
        "description": "A time-tested design favored by traditional gunslingers, the multiple barrels on this pistol mechanically rotate while firing.",
        "source": "Player Core",
        "category": "Martial Ranged Weapon"
      },
      {
        "name": "Rotolaser",
        "level": 0,
        "price": 60,
        "damage": "1d8 F",
        "range": "30 ft.",
        "reload": 1,
        "bulk": "2",
        "hands": "2",
        "magazine": "10 charges",
        "expend": 1,
        "upgrades": 1,
        "group": "Laser",
        "traits": ["Automatic", "Tech"],
        "description": "A rotolaser fires multiple beams of plasma at once. This massive assault rifle has a set of rotating barrels.",
        "source": "Player Core",
        "category": "Martial Ranged Weapon"
      },
      {
        "name": "Shirren-eye rifle",
        "level": 0,
        "price": 80,
        "damage": "1d10 P",
        "range": "120 ft.",
        "reload": 1,
        "bulk": "1",
        "hands": "2",
        "magazine": "1 projectile",
        "expend": 1,
        "upgrades": 1,
        "group": "Sniper",
        "traits": ["Analog", "Deadly d12", "Kickback", "Unwieldy", "Volley 30 ft."],
        "description": "This sniper rifle comes with a compound technological scope that allows snipers to adjust focus with natural eye movements.",
        "source": "Player Core",
        "category": "Martial Ranged Weapon"
      },
      {
        "name": "Shuriken drone",
        "level": 0,
        "price": 5,
        "damage": "1d4 P",
        "range": "40 ft.",
        "reload": 0,
        "bulk": "L",
        "hands": "1",
        "magazine": "-",
        "expend": "-",
        "upgrades": 1,
        "group": "Dart",
        "traits": ["Agile", "Tech", "Thrown", "Recovery"],
        "description": "This star-shaped weapon surrounds a tiny single rotor drone designed to return to its thrower if it doesn’t hit its target.",
        "source": "Player Core",
        "category": "Martial Ranged Weapon"
      },
      {
        "name": "Singing coil",
        "level": 0,
        "price": 70,
        "damage": "1d8 E",
        "range": "40 ft.",
        "reload": 1,
        "bulk": "2",
        "hands": "2",
        "magazine": "10 charges",
        "expend": 5,
        "upgrades": 1,
        "group": "Shock",
        "traits": ["Area (line)", "Professional (Performance)", "Tech", "Unwieldy"],
        "description": "Resembling a resonant transformer circuit, this weaponized stringed instrument produces sound by using high-frequency alternating currents.",
        "source": "Player Core",
        "category": "Martial Ranged Weapon"
      },
      {
        "name": "Stellar cannon",
        "level": 0,
        "price": 40,
        "damage": "1d10 P",
        "range": "50 ft.",
        "reload": 1,
        "bulk": "2",
        "hands": "2",
        "magazine": "8 projectiles",
        "expend": 1,
        "upgrades": 1,
        "group": "Projectile",
        "traits": ["Analog", "Area (burst 10 ft.)", "Unwieldy"],
        "description": "The rounds of this portable cannon are loaded with carefully positioned mini-missiles packed with flechettes.",
        "source": "Player Core",
        "category": "Martial Ranged Weapon"
      },
      {
        "name": "Zero cannon",
        "level": 0,
        "price": 80,
        "damage": "1d10 C",
        "range": "40 ft.",
        "reload": 1,
        "bulk": "2",
        "hands": "2",
        "magazine": "10 chem",
        "expend": 2,
        "upgrades": 1,
        "group": "Cryo",
        "traits": ["Area (line)", "Tech", "Unwieldy"],
        "description": "This triple-barreled cannon’s generator churns rapidly, circulating coolant into a blast of endothermic energy.",
        "source": "Player Core",
        "category": "Martial Ranged Weapon"
      }
    ],
    "advancedRanged": [
      {
        "name": "Aeon rifle",
        "level": 0,
        "price": 30,
        "damage": "1d10 F",
        "range": "60 ft.",
        "reload": 1,
        "bulk": "1",
        "hands": "2",
        "magazine": "10 charges",
        "expend": 1,
        "upgrades": 0,
        "group": "Laser",
        "traits": ["Aeon", "Caster", "Tech"],
        "description": "A mainstay of the Azlanti Star Empire, this sleek laser rifle includes a slot for aeon stones to enhance and focus the intensity of its beams.",
        "source": "Player Core",
        "category": "Advanced Ranged Weapon"
      },
      {
        "name": "Artillery laser",
        "level": 0,
        "price": 60,
        "damage": "1d10 F",
        "range": "60 ft.",
        "reload": 1,
        "bulk": "2",
        "hands": "2",
        "magazine": "10 charges",
        "expend": 2,
        "upgrades": 1,
        "group": "Laser",
        "traits": ["Critical (flame)", "Forceful", "Razing", "Tech"],
        "description": "The fast-firing and continuous beams of this laser cannon converge on the target to create enough heat to melt a steel door into slag.",
        "source": "Player Core",
        "category": "Advanced Ranged Weapon"
      },
      {
        "name": "Card slinger",
        "level": 0,
        "price": 26,
        "damage": "1d4 P",
        "range": "30 ft.",
        "reload": 1,
        "bulk": "L",
        "hands": "1",
        "magazine": "7 projectiles",
        "expend": 1,
        "upgrades": 1,
        "group": "Dart",
        "traits": ["Agile", "Concealable", "Deadly d8", "Professional (Deception)", "Tech"],
        "description": "This ceramic weapon sharpens and fires playing cards, such as those from an infinity deck.",
        "source": "Player Core",
        "category": "Advanced Ranged Weapon"
      },
      {
        "name": "Gyrojet pistol",
        "level": 0,
        "price": 30,
        "damage": "1d6 B",
        "range": "40 ft.",
        "reload": 1,
        "bulk": "1",
        "hands": "1",
        "magazine": "4 projectiles",
        "expend": 1,
        "upgrades": 1,
        "group": "Projectile",
        "traits": ["Analog", "Ranged shove", "Ranged trip"],
        "description": "Valued for its stopping power, this pistol sports a large caliber reinforced barrel designed to shoot tiny rockets capable of knocking enemies to the ground.",
        "source": "Player Core",
        "category": "Advanced Ranged Weapon"
      },
      {
        "name": "Magnetar rifle",
        "level": 0,
        "price": 45,
        "damage": "1d12 P",
        "range": "60 ft.",
        "reload": 1,
        "bulk": "2",
        "hands": "2",
        "magazine": "30 projectiles",
        "expend": 1,
        "upgrades": 1,
        "group": "Projectile",
        "traits": ["Analog", "Automatic"],
        "description": "This rifle uses powerful electromagnets to accelerate simple slugs into deadly, highly accurate projectiles.",
        "source": "Player Core",
        "category": "Advanced Ranged Weapon"
      },
      {
        "name": "Plasma cannon",
        "level": 0,
        "price": 80,
        "damage": "1d12 F",
        "range": "40 ft.",
        "reload": 1,
        "bulk": "2",
        "hands": "2",
        "magazine": "10 charges",
        "expend": 2,
        "upgrades": 1,
        "group": "Plasma",
        "traits": ["Area (burst 10 ft.)", "Tech", "Unwieldy"],
        "description": "This long-barreled weapon shoots charges of ionized gas that explode in a blast of superheated plasma.",
        "source": "Player Core",
        "category": "Advanced Ranged Weapon"
      },
      {
        "name": "Screamer",
        "level": 0,
        "price": 80,
        "damage": "1d12 So",
        "range": "15 ft.",
        "reload": 1,
        "bulk": "2",
        "hands": "2",
        "magazine": "10 charges",
        "expend": 2,
        "upgrades": 1,
        "group": "Sonic",
        "traits": ["Area (cone)", "Tech", "Unwieldy"],
        "description": "Resembling a large directional speaker held in two hands, a screamer produces a deafening boom.",
        "source": "Player Core",
        "category": "Advanced Ranged Weapon"
      },
      {
        "name": "Starfall pistol",
        "level": 0,
        "price": 30,
        "damage": "1d6 F",
        "range": "20 ft.",
        "reload": 1,
        "bulk": "L",
        "hands": "1",
        "magazine": "10 charges",
        "expend": 5,
        "upgrades": 1,
        "group": "Plasma",
        "traits": ["Area (line)", "Tech", "Unwieldy"],
        "description": "While originally a kit-bashed plasma caster, the commercial models fire streams of superheated plasma.",
        "source": "Player Core",
        "category": "Advanced Ranged Weapon"
      },
      {
        "name": "Streetsweeper",
        "level": 0,
        "price": 60,
        "damage": "1d10 So",
        "range": "40 ft.",
        "reload": 1,
        "bulk": "2",
        "hands": "2",
        "magazine": "10 charges",
        "expend": 2,
        "upgrades": 1,
        "group": "Sonic",
        "traits": ["Boost 1d10", "Ranged trip", "Tech"],
        "description": "This enormous portable cannon uses speakers to broadcast dense ultrasonic waves powerful enough to sweep a street clean.",
        "source": "Player Core",
        "category": "Advanced Ranged Weapon"
      }
    ]
  }
}